departments/__init__.py
departments/admin.py
departments/apps.py
departments/static/css/departments/medicio_ds.css
departments/static/css/departments/medilab_ds.css
departments/templates/departments/_common.html
departments/templates/departments/medicio_ds.html
departments/templates/departments/medilab_ds.html
departments/templatetags/__init__.py
departments/templatetags/departments_tags.py
django_departments_ds-0.0.1.dist-info/LICENSE
django_departments_ds-0.0.1.dist-info/METADATA
django_departments_ds-0.0.1.dist-info/WHEEL
django_departments_ds-0.0.1.dist-info/top_level.txt
django_departments_ds-0.0.1.dist-info/RECORD
